odoo/addons/invoice_paid_before/README.rst
odoo/addons/invoice_paid_before/__init__.py
odoo/addons/invoice_paid_before/__manifest__.py
odoo/addons/invoice_paid_before/hooks.py
odoo/addons/invoice_paid_before/i18n/es.po
odoo/addons/invoice_paid_before/models/__init__.py
odoo/addons/invoice_paid_before/models/account_move.py
odoo/addons/invoice_paid_before/static/description/icon.png
odoo14_addon_invoice_paid_before-14.0.1.0.0.dist-info/METADATA
odoo14_addon_invoice_paid_before-14.0.1.0.0.dist-info/WHEEL
odoo14_addon_invoice_paid_before-14.0.1.0.0.dist-info/top_level.txt
odoo14_addon_invoice_paid_before-14.0.1.0.0.dist-info/RECORD
